cashcow/__init__.py
cashcow/constants.py
cashcow/models/__init__.py
cashcow/models/account.py
cashcow/models/base.py
cashcow/models/connection.py
cashcow/models/user.py
cashcow_core-0.1.1.dist-info/LICENSE
cashcow_core-0.1.1.dist-info/METADATA
cashcow_core-0.1.1.dist-info/WHEEL
cashcow_core-0.1.1.dist-info/RECORD
