Metadata-Version: 2.1
Name: cashcow-core
Version: 0.1.1
Summary: 
License: MIT
Author: Soju06
Author-email: qlskssk@gmail.com
Requires-Python: >=3.12,<4.0
Classifier: License :: OSI Approved :: MIT License
Classifier: Programming Language :: Python :: 3
Classifier: Programming Language :: Python :: 3.12
Classifier: Programming Language :: Python :: 3.13
Requires-Dist: asyncpg (>=0.30.0,<0.31.0)
Requires-Dist: sqlalchemy (>=2.0.36,<3.0.0)
